[
  {
    "content": "G1: Inspeccionar el output de run_backtest",
    "status": "completed"
  },
  {
    "content": "G2: Crear services/football_calibration_diagnostics.py",
    "status": "completed"
  },
  {
    "content": "G3: Extender engine — predictions[] en modo with-odds + campos market_implied_raw/devig + odd_open/close",
    "status": "completed"
  },
  {
    "content": "G4: Script run_d7_calibration_diagnostics.py + 9 reportes generados",
    "status": "completed"
  },
  {
    "content": "G5: Endpoints GET /api/football/diagnostics/calibration[/index]",
    "status": "completed"
  },
  {
    "content": "G6: Panel UI CalibrationDiagnosticsPanel.jsx + página /diagnostics/calibration",
    "status": "completed"
  },
  {
    "content": "G7: 16 tests verde (incluyen los 4 escenarios de la rúbrica + endpoints)",
    "status": "completed"
  },
  {
    "content": "G8: pytest backend completo → 3666 passing, 0 regresiones",
    "status": "completed"
  },
  {
    "content": "G9: Entregar diagnóstico al usuario + interpretación usando su rúbrica",
    "status": "in_progress"
  }
]