[
  {
    "content": "Fix two-way player handling in _is_offensive_role (P/DH should be offensive)",
    "status": "completed"
  },
  {
    "content": "Run pytest suite — verify all tests green (target file + regressions)",
    "status": "completed"
  },
  {
    "content": "Add hydrate_team_offensive_roster() helper in mlb_stats_api.py (active roster with hitting stats, with cache)",
    "status": "completed"
  },
  {
    "content": "Integrate compute_offensive_injury_impact into mlb_day_orchestrator.py (apply multipliers, persist pick_payload + pipeline_meta)",
    "status": "completed"
  },
  {
    "content": "Build collapsible OffensiveInjuryImpactPanel.jsx (LOW=green, MEDIUM=amber, HIGH=red) mirroring TailRiskPanel pattern",
    "status": "completed"
  },
  {
    "content": "Wire panel into MatchCard.jsx",
    "status": "completed"
  },
  {
    "content": "Backend + Frontend testing via testing_agent (end-to-end validation)",
    "status": "completed"
  },
  {
    "content": "Update plan.md with final state",
    "status": "completed"
  }
]